biketrauma/__init__.py
biketrauma/io/Load_db.py
biketrauma/preprocess/format_date.py
biketrauma/preprocess/get_accident.py
biketrauma/vis/plot_location.py
biketrauma_kk-0.0.1.dist-info/METADATA
biketrauma_kk-0.0.1.dist-info/WHEEL
biketrauma_kk-0.0.1.dist-info/top_level.txt
biketrauma_kk-0.0.1.dist-info/RECORD
