Metadata-Version: 2.1
Name: biketrauma-kk
Version: 0.0.1
Summary: Visualization of a bicycle accident db
Home-page: http://github.com/Kenjy-K/packaging_tutorial.git
Author: Kenjy-K
Author-email: kenjy.koan@gmail.com
License: MIT
Platform: UNKNOWN
